{
  "Category": "Inventory_and_Production",
  "TableName": "AIT1",
  "Description": "Item - Prices \n - History",
  "PrimaryKeys": [
    "ItemCode",
    "PriceList",
    "LogInstanc"
  ],
  "Fields": [
    {
      "Field": "ItemCode",
      "Description": "Item Number",
      "Related": "OITM",
      "DefaultValue": "",
      "ValidValues": "",
      "SqlType": "nvarchar",
      "SqlSize": 20,
      "IsNullable": false,
      "IsPrimaryKey": true,
      "IsIdentity": false
    },
    {
      "Field": "PriceList",
      "Description": "Price List No.",
      "Related": "OPLN",
      "DefaultValue": "",
      "ValidValues": "",
      "SqlType": "smallint",
      "SqlSize": null,
      "IsNullable": false,
      "IsPrimaryKey": true,
      "IsIdentity": false
    },
    {
      "Field": "Price",
      "Description": "Price List",
      "Related": "",
      "DefaultValue": "",
      "ValidValues": "",
      "SqlType": "numeric",
      "SqlSize": null,
      "IsNullable": true,
      "IsPrimaryKey": false,
      "IsIdentity": false
    },
    {
      "Field": "Currency",
      "Description": "Price List Currency",
      "Related": "",
      "DefaultValue": "",
      "ValidValues": "",
      "SqlType": "nvarchar",
      "SqlSize": 3,
      "IsNullable": true,
      "IsPrimaryKey": false,
      "IsIdentity": false
    },
    {
      "Field": "Ovrwritten",
      "Description": "Manual Price Update",
      "Related": "",
      "DefaultValue": "N",
      "ValidValues": [
        [
          "Y",
          "Yes"
        ],
        [
          "N",
          "No"
        ]
      ],
      "SqlType": "char",
      "SqlSize": 1,
      "IsNullable": true,
      "IsPrimaryKey": false,
      "IsIdentity": false
    },
    {
      "Field": "Factor",
      "Description": "Factor",
      "Related": "",
      "DefaultValue": "",
      "ValidValues": "",
      "SqlType": "numeric",
      "SqlSize": null,
      "IsNullable": true,
      "IsPrimaryKey": false,
      "IsIdentity": false
    },
    {
      "Field": "LogInstanc",
      "Description": "Log Instance",
      "Related": "",
      "DefaultValue": "0",
      "ValidValues": "",
      "SqlType": "int",
      "SqlSize": null,
      "IsNullable": false,
      "IsPrimaryKey": true,
      "IsIdentity": false
    },
    {
      "Field": "ObjType",
      "Description": "Object",
      "Related": "",
      "DefaultValue": "",
      "ValidValues": "",
      "SqlType": "nvarchar",
      "SqlSize": 20,
      "IsNullable": true,
      "IsPrimaryKey": false,
      "IsIdentity": false
    }
  ]
}