{
  "Category": "Finance",
  "TableName": "OCDC",
  "Description": "Cash Discount",
  "PrimaryKeys": [
    "Code"
  ],
  "Fields": [
    {
      "Field": "Code",
      "Description": "Code",
      "Related": "",
      "DefaultValue": "",
      "ValidValues": "",
      "SqlType": "nvarchar",
      "SqlSize": 20,
      "IsNullable": false,
      "IsPrimaryKey": true,
      "IsIdentity": false
    },
    {
      "Field": "TableDesc",
      "Description": "Name",
      "Related": "",
      "DefaultValue": "",
      "ValidValues": "",
      "SqlType": "nvarchar",
      "SqlSize": 100,
      "IsNullable": true,
      "IsPrimaryKey": false,
      "IsIdentity": false
    },
    {
      "Field": "ByDate",
      "Description": "By Date",
      "Related": "",
      "DefaultValue": "N",
      "ValidValues": [
        [
          "Y",
          "Yes"
        ],
        [
          "N",
          "No"
        ]
      ],
      "SqlType": "char",
      "SqlSize": 1,
      "IsNullable": true,
      "IsPrimaryKey": false,
      "IsIdentity": false
    },
    {
      "Field": "Freight",
      "Description": "Freight",
      "Related": "",
      "DefaultValue": "N",
      "ValidValues": [
        [
          "Y",
          "Yes"
        ],
        [
          "N",
          ""
        ]
      ],
      "SqlType": "char",
      "SqlSize": 1,
      "IsNullable": true,
      "IsPrimaryKey": false,
      "IsIdentity": false
    },
    {
      "Field": "Tax",
      "Description": "Tax",
      "Related": "",
      "DefaultValue": "N",
      "ValidValues": [
        [
          "Y",
          "Yes"
        ],
        [
          "N",
          "No"
        ]
      ],
      "SqlType": "char",
      "SqlSize": 1,
      "IsNullable": true,
      "IsPrimaryKey": false,
      "IsIdentity": false
    },
    {
      "Field": "VatCrctn",
      "Description": "VAT Correction",
      "Related": "",
      "DefaultValue": "N",
      "ValidValues": [
        [
          "Y",
          "Yes"
        ],
        [
          "N",
          "No"
        ]
      ],
      "SqlType": "char",
      "SqlSize": 1,
      "IsNullable": true,
      "IsPrimaryKey": false,
      "IsIdentity": false
    }
  ]
}