{
  "Category": "Inventory_and_Production",
  "TableName": "OMRC",
  "Description": "Manufacturers",
  "PrimaryKeys": [
    "FirmCode"
  ],
  "Fields": [
    {
      "Field": "FirmCode",
      "Description": "Code",
      "Related": "",
      "DefaultValue": "",
      "ValidValues": "",
      "SqlType": "smallint",
      "SqlSize": null,
      "IsNullable": false,
      "IsPrimaryKey": true,
      "IsIdentity": false
    },
    {
      "Field": "FirmName",
      "Description": "Manufacturer Name",
      "Related": "",
      "DefaultValue": "",
      "ValidValues": "",
      "SqlType": "nvarchar",
      "SqlSize": 30,
      "IsNullable": false,
      "IsPrimaryKey": false,
      "IsIdentity": false
    },
    {
      "Field": "DataSource",
      "Description": "Data Source",
      "Related": "",
      "DefaultValue": "N",
      "ValidValues": [
        [
          "N",
          "Unknown"
        ],
        [
          "I",
          "Interface"
        ],
        [
          "U",
          "Update"
        ],
        [
          "M",
          "Import"
        ],
        [
          "O",
          "DI API"
        ],
        [
          "A",
          "Doc. Generation Wizard"
        ],
        [
          "D",
          "Restore Wizard"
        ],
        [
          "P",
          "Partner Implementation"
        ],
        [
          "T",
          "Year Transfer"
        ]
      ],
      "SqlType": "char",
      "SqlSize": 1,
      "IsNullable": true,
      "IsPrimaryKey": false,
      "IsIdentity": false
    },
    {
      "Field": "UserSign",
      "Description": "User Signature",
      "Related": "OUSR",
      "DefaultValue": "",
      "ValidValues": "",
      "SqlType": "smallint",
      "SqlSize": null,
      "IsNullable": true,
      "IsPrimaryKey": false,
      "IsIdentity": false
    }
  ]
}