{
  "Category": "Banking",
  "TableName": "OPEX",
  "Description": "Payment Results \n Table",
  "PrimaryKeys": [
    "AbsEntry"
  ],
  "Fields": [
    {
      "Field": "AbsEntry",
      "Description": "Internal Number",
      "Related": "",
      "DefaultValue": "",
      "ValidValues": "",
      "SqlType": "int",
      "SqlSize": null,
      "IsNullable": false,
      "IsPrimaryKey": true,
      "IsIdentity": false
    },
    {
      "Field": "PayRunDate",
      "Description": "Date of Payment Run",
      "Related": "",
      "DefaultValue": "",
      "ValidValues": "",
      "SqlType": "datetime",
      "SqlSize": null,
      "IsNullable": true,
      "IsPrimaryKey": false,
      "IsIdentity": false
    },
    {
      "Field": "VendorNum",
      "Description": "Vendor Code",
      "Related": "",
      "DefaultValue": "",
      "ValidValues": "",
      "SqlType": "nvarchar",
      "SqlSize": 15,
      "IsNullable": true,
      "IsPrimaryKey": false,
      "IsIdentity": false
    },
    {
      "Field": "CustNum",
      "Description": "Customer Code",
      "Related": "",
      "DefaultValue": "",
      "ValidValues": "",
      "SqlType": "nvarchar",
      "SqlSize": 15,
      "IsNullable": true,
      "IsPrimaryKey": false,
      "IsIdentity": false
    },
    {
      "Field": "PaymMethod",
      "Description": "Payment Means",
      "Related": "",
      "DefaultValue": "",
      "ValidValues": "",
      "SqlType": "nvarchar",
      "SqlSize": 15,
      "IsNullable": true,
      "IsPrimaryKey": false,
      "IsIdentity": false
    },
    {
      "Field": "PaymDocNum",
      "Description": "Payment Document No.",
      "Related": "",
      "DefaultValue": "",
      "ValidValues": "",
      "SqlType": "int",
      "SqlSize": null,
      "IsNullable": true,
      "IsPrimaryKey": false,
      "IsIdentity": false
    },
    {
      "Field": "FiscalYear",
      "Description": "Fiscal Year",
      "Related": "",
      "DefaultValue": "",
      "ValidValues": "",
      "SqlType": "datetime",
      "SqlSize": null,
      "IsNullable": true,
      "IsPrimaryKey": false,
      "IsIdentity": false
    },
    {
      "Field": "Country",
      "Description": "Company Country",
      "Related": "",
      "DefaultValue": "",
      "ValidValues": "",
      "SqlType": "nvarchar",
      "SqlSize": 3,
      "IsNullable": true,
      "IsPrimaryKey": false,
      "IsIdentity": false
    },
    {
      "Field": "CompTaxNum",
      "Description": "Company Tax Number",
      "Related": "",
      "DefaultValue": "",
      "ValidValues": "",
      "SqlType": "nvarchar",
      "SqlSize": 32,
      "IsNullable": true,
      "IsPrimaryKey": false,
      "IsIdentity": false
    },
    {
      "Field": "PayeeName",
      "Description": "Payee Name",
      "Related": "",
      "DefaultValue": "",
      "ValidValues": "",
      "SqlType": "nvarchar",
      "SqlSize": 100,
      "IsNullable": true,
      "IsPrimaryKey": false,
      "IsIdentity": false
    },
    {
      "Field": "PayeeZip",
      "Description": "Payee Zip Code",
      "Related": "",
      "DefaultValue": "",
      "ValidValues": "",
      "SqlType": "nvarchar",
      "SqlSize": 20,
      "IsNullable": true,
      "IsPrimaryKey": false,
      "IsIdentity": false
    },
    {
      "Field": "PayeeCity",
      "Description": "Payee City",
      "Related": "",
      "DefaultValue": "",
      "ValidValues": "",
      "SqlType": "nvarchar",
      "SqlSize": 100,
      "IsNullable": true,
      "IsPrimaryKey": false,
      "IsIdentity": false
    },
    {
      "Field": "PayeeStree",
      "Description": "Payee Street",
      "Related": "",
      "DefaultValue": "",
      "ValidValues": "",
      "SqlType": "nvarchar",
      "SqlSize": 100,
      "IsNullable": true,
      "IsPrimaryKey": false,
      "IsIdentity": false
    },
    {
      "Field": "PayCountry",
      "Description": "Payee Country",
      "Related": "",
      "DefaultValue": "",
      "ValidValues": "",
      "SqlType": "nvarchar",
      "SqlSize": 3,
      "IsNullable": true,
      "IsPrimaryKey": false,
      "IsIdentity": false
    },
    {
      "Field": "PayeeState",
      "Description": "Payee State",
      "Related": "",
      "DefaultValue": "",
      "ValidValues": "",
      "SqlType": "nvarchar",
      "SqlSize": 3,
      "IsNullable": true,
      "IsPrimaryKey": false,
      "IsIdentity": false
    },
    {
      "Field": "PayBnkName",
      "Description": "Payee Bank Name",
      "Related": "",
      "DefaultValue": "",
      "ValidValues": "",
      "SqlType": "nvarchar",
      "SqlSize": 250,
      "IsNullable": true,
      "IsPrimaryKey": false,
      "IsIdentity": false
    },
    {
      "Field": "PayBankZip",
      "Description": "Payee Bank Zip Code",
      "Related": "",
      "DefaultValue": "",
      "ValidValues": "",
      "SqlType": "nvarchar",
      "SqlSize": 20,
      "IsNullable": true,
      "IsPrimaryKey": false,
      "IsIdentity": false
    },
    {
      "Field": "PayBnkCity",
      "Description": "Payee Bank City",
      "Related": "",
      "DefaultValue": "",
      "ValidValues": "",
      "SqlType": "nvarchar",
      "SqlSize": 100,
      "IsNullable": true,
      "IsPrimaryKey": false,
      "IsIdentity": false
    },
    {
      "Field": "PayBnkStr",
      "Description": "Payee Bank Street",
      "Related": "",
      "DefaultValue": "",
      "ValidValues": "",
      "SqlType": "nvarchar",
      "SqlSize": 100,
      "IsNullable": true,
      "IsPrimaryKey": false,
      "IsIdentity": false
    },
    {
      "Field": "PayBnkCntr",
      "Description": "Payee Bank Country",
      "Related": "",
      "DefaultValue": "",
      "ValidValues": "",
      "SqlType": "nvarchar",
      "SqlSize": 3,
      "IsNullable": true,
      "IsPrimaryKey": false,
      "IsIdentity": false
    },
    {
      "Field": "PayBankAct",
      "Description": "Payee Bank Account",
      "Related": "",
      "DefaultValue": "",
      "ValidValues": "",
      "SqlType": "nvarchar",
      "SqlSize": 50,
      "IsNullable": true,
      "IsPrimaryKey": false,
      "IsIdentity": false
    },
    {
      "Field": "PayBnkCode",
      "Description": "Payee Bank Code",
      "Related": "",
      "DefaultValue": "",
      "ValidValues": "",
      "SqlType": "nvarchar",
      "SqlSize": 30,
      "IsNullable": true,
      "IsPrimaryKey": false,
      "IsIdentity": false
    },
    {
      "Field": "PayBnkCtrl",
      "Description": "Payee Bank Control Number",
      "Related": "",
      "DefaultValue": "",
      "ValidValues": "",
      "SqlType": "nvarchar",
      "SqlSize": 2,
      "IsNullable": true,
      "IsPrimaryKey": false,
      "IsIdentity": false
    },
    {
      "Field": "PayBnkSwif",
      "Description": "Payee Bank BIC/SWIFT Code",
      "Related": "",
      "DefaultValue": "",
      "ValidValues": "",
      "SqlType": "nvarchar",
      "SqlSize": 50,
      "IsNullable": true,
      "IsPrimaryKey": false,
      "IsIdentity": false
    },
    {
      "Field": "PayBnkIBAN",
      "Description": "Payee Bank IBAN",
      "Related": "",
      "DefaultValue": "",
      "ValidValues": "",
      "SqlType": "nvarchar",
      "SqlSize": 50,
      "IsNullable": true,
      "IsPrimaryKey": false,
      "IsIdentity": false
    },
    {
      "Field": "PymPostDat",
      "Description": "Payment Posting Date",
      "Related": "",
      "DefaultValue": "",
      "ValidValues": "",
      "SqlType": "datetime",
      "SqlSize": null,
      "IsNullable": true,
      "IsPrimaryKey": false,
      "IsIdentity": false
    },
    {
      "Field": "PymBnkAcct",
      "Description": "Payment Bank Account",
      "Related": "",
      "DefaultValue": "",
      "ValidValues": "",
      "SqlType": "nvarchar",
      "SqlSize": 50,
      "IsNullable": true,
      "IsPrimaryKey": false,
      "IsIdentity": false
    },
    {
      "Field": "PymBnkCntr",
      "Description": "Payment Bank Country",
      "Related": "",
      "DefaultValue": "",
      "ValidValues": "",
      "SqlType": "nvarchar",
      "SqlSize": 3,
      "IsNullable": true,
      "IsPrimaryKey": false,
      "IsIdentity": false
    },
    {
      "Field": "PymBnkCode",
      "Description": "Payment Bank Code",
      "Related": "",
      "DefaultValue": "",
      "ValidValues": "",
      "SqlType": "nvarchar",
      "SqlSize": 30,
      "IsNullable": true,
      "IsPrimaryKey": false,
      "IsIdentity": false
    },
    {
      "Field": "PymBnkIBAN",
      "Description": "Payment Bank IBAN",
      "Related": "",
      "DefaultValue": "",
      "ValidValues": "",
      "SqlType": "nvarchar",
      "SqlSize": 50,
      "IsNullable": true,
      "IsPrimaryKey": false,
      "IsIdentity": false
    },
    {
      "Field": "PymGLAcct",
      "Description": "Payment G/L Account",
      "Related": "",
      "DefaultValue": "",
      "ValidValues": "",
      "SqlType": "nvarchar",
      "SqlSize": 15,
      "IsNullable": true,
      "IsPrimaryKey": false,
      "IsIdentity": false
    },
    {
      "Field": "Currency",
      "Description": "Main Currency",
      "Related": "",
      "DefaultValue": "",
      "ValidValues": "",
      "SqlType": "nvarchar",
      "SqlSize": 3,
      "IsNullable": true,
      "IsPrimaryKey": false,
      "IsIdentity": false
    },
    {
      "Field": "PymDocAmnt",
      "Description": "Payment Document Amount (LC)",
      "Related": "",
      "DefaultValue": "",
      "ValidValues": "",
      "SqlType": "numeric",
      "SqlSize": null,
      "IsNullable": true,
      "IsPrimaryKey": false,
      "IsIdentity": false
    },
    {
      "Field": "PymDocCurr",
      "Description": "Payment Document Currency",
      "Related": "",
      "DefaultValue": "",
      "ValidValues": "",
      "SqlType": "nvarchar",
      "SqlSize": 3,
      "IsNullable": true,
      "IsPrimaryKey": false,
      "IsIdentity": false
    },
    {
      "Field": "PymDcAmtFC",
      "Description": "Payment Document Amount (FC)",
      "Related": "",
      "DefaultValue": "",
      "ValidValues": "",
      "SqlType": "numeric",
      "SqlSize": null,
      "IsNullable": true,
      "IsPrimaryKey": false,
      "IsIdentity": false
    },
    {
      "Field": "PymCshDsct",
      "Description": "Cash Discount in Payment Doc",
      "Related": "",
      "DefaultValue": "",
      "ValidValues": "",
      "SqlType": "numeric",
      "SqlSize": null,
      "IsNullable": true,
      "IsPrimaryKey": false,
      "IsIdentity": false
    },
    {
      "Field": "PyCshDscFC",
      "Description": "Cash Discount in Payment Doc",
      "Related": "",
      "DefaultValue": "",
      "ValidValues": "",
      "SqlType": "numeric",
      "SqlSize": null,
      "IsNullable": true,
      "IsPrimaryKey": false,
      "IsIdentity": false
    },
    {
      "Field": "PymNumOfPa",
      "Description": "Number of Items Paid",
      "Related": "",
      "DefaultValue": "",
      "ValidValues": "",
      "SqlType": "int",
      "SqlSize": null,
      "IsNullable": true,
      "IsPrimaryKey": false,
      "IsIdentity": false
    },
    {
      "Field": "PymDocRate",
      "Description": "Payment Document Exchange Rate",
      "Related": "",
      "DefaultValue": "",
      "ValidValues": "",
      "SqlType": "numeric",
      "SqlSize": null,
      "IsNullable": true,
      "IsPrimaryKey": false,
      "IsIdentity": false
    },
    {
      "Field": "Status",
      "Description": "Status",
      "Related": "",
      "DefaultValue": "O",
      "ValidValues": [
        [
          "O",
          "Open"
        ],
        [
          "C",
          "Closed"
        ]
      ],
      "SqlType": "char",
      "SqlSize": 1,
      "IsNullable": true,
      "IsPrimaryKey": false,
      "IsIdentity": false
    },
    {
      "Field": "PaymWizCod",
      "Description": "Payment Wizard Code",
      "Related": "OPWZ",
      "DefaultValue": "",
      "ValidValues": "",
      "SqlType": "int",
      "SqlSize": null,
      "IsNullable": true,
      "IsPrimaryKey": false,
      "IsIdentity": false
    },
    {
      "Field": "InstrucKey",
      "Description": "Instruction Key",
      "Related": "",
      "DefaultValue": "",
      "ValidValues": "",
      "SqlType": "nvarchar",
      "SqlSize": 30,
      "IsNullable": true,
      "IsPrimaryKey": false,
      "IsIdentity": false
    },
    {
      "Field": "CllctAutho",
      "Description": "Collection Authorization",
      "Related": "",
      "DefaultValue": "",
      "ValidValues": "",
      "SqlType": "char",
      "SqlSize": 1,
      "IsNullable": true,
      "IsPrimaryKey": false,
      "IsIdentity": false
    },
    {
      "Field": "PayBnkPost",
      "Description": "Payee Bank Post Office",
      "Related": "",
      "DefaultValue": "",
      "ValidValues": "",
      "SqlType": "char",
      "SqlSize": 1,
      "IsNullable": true,
      "IsPrimaryKey": false,
      "IsIdentity": false
    },
    {
      "Field": "PayBnkChNo",
      "Description": "Payee Bank Next Check No.",
      "Related": "",
      "DefaultValue": "",
      "ValidValues": "",
      "SqlType": "int",
      "SqlSize": null,
      "IsNullable": true,
      "IsPrimaryKey": false,
      "IsIdentity": false
    },
    {
      "Field": "PayBnkHsBk",
      "Description": "Payee Bank House Bank",
      "Related": "",
      "DefaultValue": "N",
      "ValidValues": [
        [
          "N",
          "No"
        ],
        [
          "Y",
          "Yes"
        ]
      ],
      "SqlType": "char",
      "SqlSize": 1,
      "IsNullable": true,
      "IsPrimaryKey": false,
      "IsIdentity": false
    },
    {
      "Field": "PayBnkBlck",
      "Description": "Payee Bank Block",
      "Related": "",
      "DefaultValue": "",
      "ValidValues": "",
      "SqlType": "nvarchar",
      "SqlSize": 100,
      "IsNullable": true,
      "IsPrimaryKey": false,
      "IsIdentity": false
    },
    {
      "Field": "PayBnkCnty",
      "Description": "Payee Bank County",
      "Related": "",
      "DefaultValue": "",
      "ValidValues": "",
      "SqlType": "nvarchar",
      "SqlSize": 100,
      "IsNullable": true,
      "IsPrimaryKey": false,
      "IsIdentity": false
    },
    {
      "Field": "PayBnkStat",
      "Description": "Payee Bank State",
      "Related": "",
      "DefaultValue": "",
      "ValidValues": "",
      "SqlType": "nvarchar",
      "SqlSize": 3,
      "IsNullable": true,
      "IsPrimaryKey": false,
      "IsIdentity": false
    },
    {
      "Field": "PayBnkBISR",
      "Description": "Payee Bank BISR",
      "Related": "",
      "DefaultValue": "N",
      "ValidValues": [
        [
          "N",
          "No"
        ],
        [
          "Y",
          "Yes"
        ]
      ],
      "SqlType": "char",
      "SqlSize": 1,
      "IsNullable": true,
      "IsPrimaryKey": false,
      "IsIdentity": false
    },
    {
      "Field": "PayBnkUsr1",
      "Description": "Payee Bank User No. 1",
      "Related": "",
      "DefaultValue": "",
      "ValidValues": "",
      "SqlType": "nvarchar",
      "SqlSize": 25,
      "IsNullable": true,
      "IsPrimaryKey": false,
      "IsIdentity": false
    },
    {
      "Field": "PayBnkUsr2",
      "Description": "Payee Bank User No. 2",
      "Related": "",
      "DefaultValue": "",
      "ValidValues": "",
      "SqlType": "nvarchar",
      "SqlSize": 25,
      "IsNullable": true,
      "IsPrimaryKey": false,
      "IsIdentity": false
    },
    {
      "Field": "PayBnkUsr3",
      "Description": "Payee Bank User No. 3",
      "Related": "",
      "DefaultValue": "",
      "ValidValues": "",
      "SqlType": "nvarchar",
      "SqlSize": 25,
      "IsNullable": true,
      "IsPrimaryKey": false,
      "IsIdentity": false
    },
    {
      "Field": "PayBnkUsr4",
      "Description": "Payee Bank User No. 4",
      "Related": "",
      "DefaultValue": "",
      "ValidValues": "",
      "SqlType": "nvarchar",
      "SqlSize": 25,
      "IsNullable": true,
      "IsPrimaryKey": false,
      "IsIdentity": false
    },
    {
      "Field": "PaymFormat",
      "Description": "Payment Format",
      "Related": "",
      "DefaultValue": "",
      "ValidValues": "",
      "SqlType": "nvarchar",
      "SqlSize": 20,
      "IsNullable": true,
      "IsPrimaryKey": false,
      "IsIdentity": false
    },
    {
      "Field": "CompName",
      "Description": "Company Name",
      "Related": "",
      "DefaultValue": "",
      "ValidValues": "",
      "SqlType": "nvarchar",
      "SqlSize": 100,
      "IsNullable": true,
      "IsPrimaryKey": false,
      "IsIdentity": false
    },
    {
      "Field": "CompAddres",
      "Description": "Company Address",
      "Related": "",
      "DefaultValue": "",
      "ValidValues": "",
      "SqlType": "nvarchar",
      "SqlSize": 254,
      "IsNullable": true,
      "IsPrimaryKey": false,
      "IsIdentity": false
    },
    {
      "Field": "CompISRBil",
      "Description": "Company ISR Biller ID",
      "Related": "",
      "DefaultValue": "",
      "ValidValues": "",
      "SqlType": "nvarchar",
      "SqlSize": 9,
      "IsNullable": true,
      "IsPrimaryKey": false,
      "IsIdentity": false
    },
    {
      "Field": "VendISRBil",
      "Description": "Vendor ISR Biller ID",
      "Related": "",
      "DefaultValue": "",
      "ValidValues": "",
      "SqlType": "nvarchar",
      "SqlSize": 9,
      "IsNullable": true,
      "IsPrimaryKey": false,
      "IsIdentity": false
    },
    {
      "Field": "AddIdNum",
      "Description": "Additional ID No.",
      "Related": "",
      "DefaultValue": "",
      "ValidValues": "",
      "SqlType": "nvarchar",
      "SqlSize": 32,
      "IsNullable": true,
      "IsPrimaryKey": false,
      "IsIdentity": false
    },
    {
      "Field": "CompOrgNum",
      "Description": "Company Organization No.",
      "Related": "",
      "DefaultValue": "",
      "ValidValues": "",
      "SqlType": "nvarchar",
      "SqlSize": 50,
      "IsNullable": true,
      "IsPrimaryKey": false,
      "IsIdentity": false
    },
    {
      "Field": "PayBnkBrnc",
      "Description": "Payee Bank Branch",
      "Related": "",
      "DefaultValue": "",
      "ValidValues": "",
      "SqlType": "nvarchar",
      "SqlSize": 50,
      "IsNullable": true,
      "IsPrimaryKey": false,
      "IsIdentity": false
    },
    {
      "Field": "PymBnkBrnc",
      "Description": "Payment Bank Branch",
      "Related": "",
      "DefaultValue": "",
      "ValidValues": "",
      "SqlType": "nvarchar",
      "SqlSize": 50,
      "IsNullable": true,
      "IsPrimaryKey": false,
      "IsIdentity": false
    },
    {
      "Field": "UserName",
      "Description": "User Name",
      "Related": "",
      "DefaultValue": "",
      "ValidValues": "",
      "SqlType": "nvarchar",
      "SqlSize": 155,
      "IsNullable": true,
      "IsPrimaryKey": false,
      "IsIdentity": false
    },
    {
      "Field": "UserEmail",
      "Description": "User E-Mail",
      "Related": "",
      "DefaultValue": "",
      "ValidValues": "",
      "SqlType": "nvarchar",
      "SqlSize": 100,
      "IsNullable": true,
      "IsPrimaryKey": false,
      "IsIdentity": false
    },
    {
      "Field": "UserPortNo",
      "Description": "User Mobile Phone No.",
      "Related": "",
      "DefaultValue": "",
      "ValidValues": "",
      "SqlType": "nvarchar",
      "SqlSize": 50,
      "IsNullable": true,
      "IsPrimaryKey": false,
      "IsIdentity": false
    },
    {
      "Field": "UserFax",
      "Description": "User Fax No.",
      "Related": "",
      "DefaultValue": "",
      "ValidValues": "",
      "SqlType": "nvarchar",
      "SqlSize": 20,
      "IsNullable": true,
      "IsPrimaryKey": false,
      "IsIdentity": false
    },
    {
      "Field": "Department",
      "Description": "User Department",
      "Related": "",
      "DefaultValue": "",
      "ValidValues": "",
      "SqlType": "smallint",
      "SqlSize": null,
      "IsNullable": true,
      "IsPrimaryKey": false,
      "IsIdentity": false
    },
    {
      "Field": "DebitMemo",
      "Description": "Debit Memo",
      "Related": "",
      "DefaultValue": "N",
      "ValidValues": [
        [
          "N",
          "No"
        ],
        [
          "Y",
          "Yes"
        ]
      ],
      "SqlType": "char",
      "SqlSize": 1,
      "IsNullable": true,
      "IsPrimaryKey": false,
      "IsIdentity": false
    },
    {
      "Field": "EuInTrnsfr",
      "Description": "EU Internal Transfer",
      "Related": "",
      "DefaultValue": "N",
      "ValidValues": [
        [
          "N",
          "No"
        ],
        [
          "Y",
          "Yes"
        ]
      ],
      "SqlType": "char",
      "SqlSize": 1,
      "IsNullable": true,
      "IsPrimaryKey": false,
      "IsIdentity": false
    },
    {
      "Field": "FilePath",
      "Description": "File Path",
      "Related": "",
      "DefaultValue": "",
      "ValidValues": "",
      "SqlType": "ntext",
      "SqlSize": 1073741823,
      "IsNullable": true,
      "IsPrimaryKey": false,
      "IsIdentity": false
    },
    {
      "Field": "OrderParty",
      "Description": "Ordering Party",
      "Related": "",
      "DefaultValue": "",
      "ValidValues": "",
      "SqlType": "nvarchar",
      "SqlSize": 30,
      "IsNullable": true,
      "IsPrimaryKey": false,
      "IsIdentity": false
    },
    {
      "Field": "PymCtrlKey",
      "Description": "Payment Bank Control Number",
      "Related": "",
      "DefaultValue": "",
      "ValidValues": "",
      "SqlType": "nvarchar",
      "SqlSize": 2,
      "IsNullable": true,
      "IsPrimaryKey": false,
      "IsIdentity": false
    },
    {
      "Field": "PayeeTaxNo",
      "Description": "Payee Tax Number",
      "Related": "",
      "DefaultValue": "",
      "ValidValues": "",
      "SqlType": "nvarchar",
      "SqlSize": 32,
      "IsNullable": true,
      "IsPrimaryKey": false,
      "IsIdentity": false
    },
    {
      "Field": "PymKeyCode",
      "Description": "Payment Key Code",
      "Related": "",
      "DefaultValue": "",
      "ValidValues": "",
      "SqlType": "nvarchar",
      "SqlSize": 6,
      "IsNullable": true,
      "IsPrimaryKey": false,
      "IsIdentity": false
    },
    {
      "Field": "PayRefDtls",
      "Description": "Payee Reference Details",
      "Related": "",
      "DefaultValue": "",
      "ValidValues": "",
      "SqlType": "nvarchar",
      "SqlSize": 20,
      "IsNullable": true,
      "IsPrimaryKey": false,
      "IsIdentity": false
    },
    {
      "Field": "FormatName",
      "Description": "Format Name",
      "Related": "",
      "DefaultValue": "",
      "ValidValues": "",
      "SqlType": "nvarchar",
      "SqlSize": 100,
      "IsNullable": true,
      "IsPrimaryKey": false,
      "IsIdentity": false
    },
    {
      "Field": "CheckPmnt",
      "Description": "Payment Done with Check",
      "Related": "",
      "DefaultValue": "N",
      "ValidValues": [
        [
          "N",
          "No"
        ],
        [
          "Y",
          "Yes"
        ]
      ],
      "SqlType": "char",
      "SqlSize": 1,
      "IsNullable": true,
      "IsPrimaryKey": false,
      "IsIdentity": false
    },
    {
      "Field": "PymBnkUsr1",
      "Description": "Payment Bank User No. 1",
      "Related": "",
      "DefaultValue": "",
      "ValidValues": "",
      "SqlType": "nvarchar",
      "SqlSize": 25,
      "IsNullable": true,
      "IsPrimaryKey": false,
      "IsIdentity": false
    },
    {
      "Field": "PymBnkUsr2",
      "Description": "Payment Bank User No. 2",
      "Related": "",
      "DefaultValue": "",
      "ValidValues": "",
      "SqlType": "nvarchar",
      "SqlSize": 25,
      "IsNullable": true,
      "IsPrimaryKey": false,
      "IsIdentity": false
    },
    {
      "Field": "PymBnkUsr3",
      "Description": "Payment Bank User No. 3",
      "Related": "",
      "DefaultValue": "",
      "ValidValues": "",
      "SqlType": "nvarchar",
      "SqlSize": 25,
      "IsNullable": true,
      "IsPrimaryKey": false,
      "IsIdentity": false
    },
    {
      "Field": "PymBnkUsr4",
      "Description": "Payment Bank User No. 4",
      "Related": "",
      "DefaultValue": "",
      "ValidValues": "",
      "SqlType": "nvarchar",
      "SqlSize": 25,
      "IsNullable": true,
      "IsPrimaryKey": false,
      "IsIdentity": false
    },
    {
      "Field": "CompStreet",
      "Description": "Company Street",
      "Related": "",
      "DefaultValue": "",
      "ValidValues": "",
      "SqlType": "nvarchar",
      "SqlSize": 100,
      "IsNullable": true,
      "IsPrimaryKey": false,
      "IsIdentity": false
    },
    {
      "Field": "CompBlock",
      "Description": "Company Block",
      "Related": "",
      "DefaultValue": "",
      "ValidValues": "",
      "SqlType": "nvarchar",
      "SqlSize": 100,
      "IsNullable": true,
      "IsPrimaryKey": false,
      "IsIdentity": false
    },
    {
      "Field": "CompCity",
      "Description": "Company City",
      "Related": "",
      "DefaultValue": "",
      "ValidValues": "",
      "SqlType": "nvarchar",
      "SqlSize": 100,
      "IsNullable": true,
      "IsPrimaryKey": false,
      "IsIdentity": false
    },
    {
      "Field": "CompZip",
      "Description": "Company Zip Code",
      "Related": "",
      "DefaultValue": "",
      "ValidValues": "",
      "SqlType": "nvarchar",
      "SqlSize": 20,
      "IsNullable": true,
      "IsPrimaryKey": false,
      "IsIdentity": false
    },
    {
      "Field": "CompCounty",
      "Description": "Company County",
      "Related": "",
      "DefaultValue": "",
      "ValidValues": "",
      "SqlType": "nvarchar",
      "SqlSize": 100,
      "IsNullable": true,
      "IsPrimaryKey": false,
      "IsIdentity": false
    },
    {
      "Field": "CompState",
      "Description": "Company State",
      "Related": "OCST",
      "DefaultValue": "",
      "ValidValues": "",
      "SqlType": "nvarchar",
      "SqlSize": 3,
      "IsNullable": true,
      "IsPrimaryKey": false,
      "IsIdentity": false
    },
    {
      "Field": "PymBCACode",
      "Description": "Payment Bank Charges",
      "Related": "OBCA",
      "DefaultValue": "",
      "ValidValues": "",
      "SqlType": "nvarchar",
      "SqlSize": 3,
      "IsNullable": true,
      "IsPrimaryKey": false,
      "IsIdentity": false
    },
    {
      "Field": "PaymDocTyp",
      "Description": "Payment Document Object Type",
      "Related": "",
      "DefaultValue": "",
      "ValidValues": "",
      "SqlType": "nvarchar",
      "SqlSize": 20,
      "IsNullable": true,
      "IsPrimaryKey": false,
      "IsIdentity": false
    }
  ]
}