{
  "Category": "Service",
  "TableName": "OQUE",
  "Description": "Queue",
  "PrimaryKeys": [
    "queueID"
  ],
  "Fields": [
    {
      "Field": "queueID",
      "Description": "Queue ID",
      "Related": "",
      "DefaultValue": "",
      "ValidValues": "",
      "SqlType": "nvarchar",
      "SqlSize": 20,
      "IsNullable": false,
      "IsPrimaryKey": true,
      "IsIdentity": false
    },
    {
      "Field": "descript",
      "Description": "Description",
      "Related": "",
      "DefaultValue": "",
      "ValidValues": "",
      "SqlType": "nvarchar",
      "SqlSize": 200,
      "IsNullable": true,
      "IsPrimaryKey": false,
      "IsIdentity": false
    },
    {
      "Field": "manager",
      "Description": "Queue Manager",
      "Related": "OUSR",
      "DefaultValue": "0",
      "ValidValues": "",
      "SqlType": "int",
      "SqlSize": null,
      "IsNullable": true,
      "IsPrimaryKey": false,
      "IsIdentity": false
    },
    {
      "Field": "email",
      "Description": "Queue E-mail",
      "Related": "",
      "DefaultValue": "",
      "ValidValues": "",
      "SqlType": "nvarchar",
      "SqlSize": 200,
      "IsNullable": true,
      "IsPrimaryKey": false,
      "IsIdentity": false
    },
    {
      "Field": "inactive",
      "Description": "Inactive",
      "Related": "",
      "DefaultValue": "N",
      "ValidValues": [
        [
          "Y",
          "Yes"
        ],
        [
          "N",
          "No"
        ]
      ],
      "SqlType": "char",
      "SqlSize": 1,
      "IsNullable": true,
      "IsPrimaryKey": false,
      "IsIdentity": false
    }
  ]
}